geoshell/__init__.py
geoshell/cli.py
geoshell/core.py
geoshell/exceptions.py
geoshell/utils.py
tests/__init__.py
tests/test_cli.py
tests/test_geoshell.py
tests/test_integration.py
geoshell-1.0.0.dist-info/METADATA
geoshell-1.0.0.dist-info/WHEEL
geoshell-1.0.0.dist-info/entry_points.txt
geoshell-1.0.0.dist-info/top_level.txt
geoshell-1.0.0.dist-info/RECORD
